scipdf/__init__.py
scipdf/py.typed
scipdf-0.0.2.dist-info/METADATA
scipdf-0.0.2.dist-info/WHEEL
scipdf-0.0.2.dist-info/top_level.txt
scipdf-0.0.2.dist-info/RECORD
